{
  "feed": [
    {
      "t": 1,
      "kind": "headline",
      "title": "Consumer Discretionary rallies on upbeat positioning.",
      "sentiment": "bullish",
      "importance": "medium"
    },
    {
      "t": 4,
      "kind": "headline",
      "title": "Consumer Discretionary rallies on upbeat positioning.",
      "sentiment": "bullish",
      "importance": "medium"
    },
    {
      "t": 6,
      "kind": "headline",
      "title": "Risk-on tone lifts Consumer Discretionary into the close.",
      "sentiment": "bullish",
      "importance": "medium"
    },
    {
      "t": 8,
      "kind": "headline",
      "title": "Consumer Discretionary catches a bid as buyers step in.",
      "sentiment": "bullish",
      "importance": "medium"
    },
    {
      "t": 21,
      "kind": "calendar",
      "title": "Nonfarm Payrolls released",
      "name": "Nonfarm Payrolls",
      "actual": 2.3,
      "forecast": 2.6,
      "prior": 2.5,
      "surprise": -0.3,
      "sentiment": "neutral",
      "importance": "high"
    },
    {
      "t": 22,
      "kind": "headline",
      "title": "Dip-buyers reward Consumer Discretionary after recent weakness.",
      "sentiment": "bullish",
      "importance": "medium"
    },
    {
      "t": 42,
      "kind": "calendar",
      "title": "FOMC Rate Decision released",
      "name": "FOMC Rate Decision",
      "actual": 2.8,
      "forecast": 2.8,
      "prior": 2.7,
      "surprise": 0.0,
      "sentiment": "neutral",
      "importance": "high"
    },
    {
      "t": 52,
      "kind": "headline",
      "title": "Caution weighs on Consumer Discretionary into the session.",
      "sentiment": "bearish",
      "importance": "high"
    },
    {
      "t": 54,
      "kind": "headline",
      "title": "Caution weighs on Consumer Discretionary into the session.",
      "sentiment": "bearish",
      "importance": "medium"
    },
    {
      "t": 63,
      "kind": "headline",
      "title": "Profit-taking drags Consumer Discretionary lower.",
      "sentiment": "bearish",
      "importance": "medium"
    },
    {
      "t": 63,
      "kind": "calendar",
      "title": "PPI released",
      "name": "PPI",
      "actual": 2.4,
      "forecast": 2.7,
      "prior": 2.6,
      "surprise": -0.3,
      "sentiment": "bullish",
      "importance": "high"
    },
    {
      "t": 71,
      "kind": "headline",
      "title": "Consumer Discretionary catches a bid as buyers step in.",
      "sentiment": "bullish",
      "importance": "medium"
    },
    {
      "t": 72,
      "kind": "headline",
      "title": "Consumer Discretionary slips as sellers take control.",
      "sentiment": "bearish",
      "importance": "medium"
    },
    {
      "t": 84,
      "kind": "headline",
      "title": "Consumer Discretionary under pressure amid risk-off rotation.",
      "sentiment": "bearish",
      "importance": "high"
    },
    {
      "t": 84,
      "kind": "calendar",
      "title": "Retail Sales released",
      "name": "Retail Sales",
      "actual": 1.9,
      "forecast": 2.1,
      "prior": 2.0,
      "surprise": -0.2,
      "sentiment": "neutral",
      "importance": "high"
    },
    {
      "t": 88,
      "kind": "headline",
      "title": "Consumer Discretionary under pressure amid risk-off rotation.",
      "sentiment": "bearish",
      "importance": "medium"
    },
    {
      "t": 89,
      "kind": "headline",
      "title": "Consumer Discretionary slips as sellers take control.",
      "sentiment": "bearish",
      "importance": "medium"
    },
    {
      "t": 93,
      "kind": "headline",
      "title": "Consumer Discretionary rallies on upbeat positioning.",
      "sentiment": "bullish",
      "importance": "medium"
    },
    {
      "t": 95,
      "kind": "headline",
      "title": "Dip-buyers reward Consumer Discretionary after recent weakness.",
      "sentiment": "bullish",
      "importance": "medium"
    },
    {
      "t": 96,
      "kind": "headline",
      "title": "Dip-buyers reward Consumer Discretionary after recent weakness.",
      "sentiment": "bullish",
      "importance": "medium"
    },
    {
      "t": 98,
      "kind": "headline",
      "title": "Consumer Discretionary slips as sellers take control.",
      "sentiment": "bearish",
      "importance": "medium"
    },
    {
      "t": 99,
      "kind": "headline",
      "title": "Caution weighs on Consumer Discretionary into the session.",
      "sentiment": "bearish",
      "importance": "high"
    },
    {
      "t": 101,
      "kind": "headline",
      "title": "Consumer Discretionary rallies on upbeat positioning.",
      "sentiment": "bullish",
      "importance": "high"
    },
    {
      "t": 104,
      "kind": "headline",
      "title": "Consumer Discretionary rallies on upbeat positioning.",
      "sentiment": "bullish",
      "importance": "medium"
    },
    {
      "t": 105,
      "kind": "calendar",
      "title": "GDP released",
      "name": "GDP",
      "actual": 2.6,
      "forecast": 2.7,
      "prior": 2.6,
      "surprise": -0.1,
      "sentiment": "neutral",
      "importance": "high"
    },
    {
      "t": 114,
      "kind": "headline",
      "title": "Consumer Discretionary catches a bid as buyers step in.",
      "sentiment": "bullish",
      "importance": "high"
    },
    {
      "t": 118,
      "kind": "headline",
      "title": "Dip-buyers reward Consumer Discretionary after recent weakness.",
      "sentiment": "bullish",
      "importance": "medium"
    },
    {
      "t": 123,
      "kind": "headline",
      "title": "Dip-buyers reward Consumer Discretionary after recent weakness.",
      "sentiment": "bullish",
      "importance": "medium"
    },
    {
      "t": 126,
      "kind": "calendar",
      "title": "CPI released",
      "name": "CPI",
      "actual": 4.0,
      "forecast": 3.9,
      "prior": 3.8,
      "surprise": 0.1,
      "sentiment": "bearish",
      "importance": "high"
    },
    {
      "t": 136,
      "kind": "headline",
      "title": "Dip-buyers reward Consumer Discretionary after recent weakness.",
      "sentiment": "bullish",
      "importance": "medium"
    },
    {
      "t": 144,
      "kind": "headline",
      "title": "Risk-on tone lifts Consumer Discretionary into the close.",
      "sentiment": "bullish",
      "importance": "medium"
    },
    {
      "t": 147,
      "kind": "calendar",
      "title": "Nonfarm Payrolls released",
      "name": "Nonfarm Payrolls",
      "actual": 3.5,
      "forecast": 3.6,
      "prior": 3.5,
      "surprise": -0.1,
      "sentiment": "neutral",
      "importance": "high"
    },
    {
      "t": 164,
      "kind": "headline",
      "title": "Dip-buyers reward Consumer Discretionary after recent weakness.",
      "sentiment": "bullish",
      "importance": "medium"
    },
    {
      "t": 168,
      "kind": "calendar",
      "title": "FOMC Rate Decision released",
      "name": "FOMC Rate Decision",
      "actual": 2.7,
      "forecast": 2.8,
      "prior": 2.7,
      "surprise": -0.1,
      "sentiment": "neutral",
      "importance": "high"
    },
    {
      "t": 170,
      "kind": "headline",
      "title": "Consumer Discretionary rallies on upbeat positioning.",
      "sentiment": "bullish",
      "importance": "medium"
    },
    {
      "t": 183,
      "kind": "headline",
      "title": "Caution weighs on Consumer Discretionary into the session.",
      "sentiment": "bearish",
      "importance": "medium"
    },
    {
      "t": 189,
      "kind": "calendar",
      "title": "PPI released",
      "name": "PPI",
      "actual": 3.1,
      "forecast": 2.8,
      "prior": 2.7,
      "surprise": 0.3,
      "sentiment": "bearish",
      "importance": "high"
    },
    {
      "t": 207,
      "kind": "headline",
      "title": "Consumer Discretionary catches a bid as buyers step in.",
      "sentiment": "bullish",
      "importance": "medium"
    },
    {
      "t": 210,
      "kind": "headline",
      "title": "Risk-on tone lifts Consumer Discretionary into the close.",
      "sentiment": "bullish",
      "importance": "medium"
    },
    {
      "t": 210,
      "kind": "calendar",
      "title": "Retail Sales released",
      "name": "Retail Sales",
      "actual": 2.2,
      "forecast": 2.4,
      "prior": 2.3,
      "surprise": -0.2,
      "sentiment": "neutral",
      "importance": "high"
    },
    {
      "t": 212,
      "kind": "headline",
      "title": "Profit-taking drags Consumer Discretionary lower.",
      "sentiment": "bearish",
      "importance": "medium"
    },
    {
      "t": 220,
      "kind": "headline",
      "title": "Consumer Discretionary under pressure amid risk-off rotation.",
      "sentiment": "bearish",
      "importance": "medium"
    },
    {
      "t": 224,
      "kind": "headline",
      "title": "Consumer Discretionary under pressure amid risk-off rotation.",
      "sentiment": "bearish",
      "importance": "medium"
    },
    {
      "t": 231,
      "kind": "calendar",
      "title": "GDP released",
      "name": "GDP",
      "actual": 2.7,
      "forecast": 2.7,
      "prior": 2.6,
      "surprise": 0.0,
      "sentiment": "neutral",
      "importance": "high"
    },
    {
      "t": 243,
      "kind": "headline",
      "title": "Consumer Discretionary catches a bid as buyers step in.",
      "sentiment": "bullish",
      "importance": "medium"
    },
    {
      "t": 246,
      "kind": "headline",
      "title": "Consumer Discretionary rallies on upbeat positioning.",
      "sentiment": "bullish",
      "importance": "medium"
    },
    {
      "t": 250,
      "kind": "headline",
      "title": "Profit-taking drags Consumer Discretionary lower.",
      "sentiment": "bearish",
      "importance": "high"
    }
  ],
  "indicators": [
    {
      "t": 0,
      "cpi_yoy": 2.3,
      "unemployment": 3.9,
      "fed_funds": 4.4,
      "ten_year": 3.6
    },
    {
      "t": 21,
      "cpi_yoy": 3.7,
      "unemployment": 4.2,
      "fed_funds": 4.7,
      "ten_year": 3.4
    },
    {
      "t": 42,
      "cpi_yoy": 1.9,
      "unemployment": 3.0,
      "fed_funds": 4.4,
      "ten_year": 4.6
    },
    {
      "t": 63,
      "cpi_yoy": 4.4,
      "unemployment": 4.6,
      "fed_funds": 5.3,
      "ten_year": 3.5
    },
    {
      "t": 84,
      "cpi_yoy": 2.0,
      "unemployment": 4.2,
      "fed_funds": 4.4,
      "ten_year": 4.3
    },
    {
      "t": 105,
      "cpi_yoy": 4.0,
      "unemployment": 4.6,
      "fed_funds": 4.2,
      "ten_year": 5.1
    },
    {
      "t": 126,
      "cpi_yoy": 2.4,
      "unemployment": 4.7,
      "fed_funds": 4.3,
      "ten_year": 3.7
    },
    {
      "t": 147,
      "cpi_yoy": 3.7,
      "unemployment": 3.1,
      "fed_funds": 3.6,
      "ten_year": 4.2
    },
    {
      "t": 168,
      "cpi_yoy": 2.7,
      "unemployment": 3.4,
      "fed_funds": 4.0,
      "ten_year": 4.1
    },
    {
      "t": 189,
      "cpi_yoy": 4.2,
      "unemployment": 3.2,
      "fed_funds": 4.0,
      "ten_year": 3.0
    },
    {
      "t": 210,
      "cpi_yoy": 3.5,
      "unemployment": 4.2,
      "fed_funds": 4.4,
      "ten_year": 4.4
    },
    {
      "t": 231,
      "cpi_yoy": 1.6,
      "unemployment": 3.3,
      "fed_funds": 5.2,
      "ten_year": 4.4
    }
  ],
  "meta": {
    "sector": "Consumer Discretionary",
    "bars": 252
  }
}